matplotlib_terminal/__init__.py
matplotlib_terminal/backend.py
matplitlib_terminal-0.1a2.dist-info/LICENSE
matplitlib_terminal-0.1a2.dist-info/METADATA
matplitlib_terminal-0.1a2.dist-info/WHEEL
matplitlib_terminal-0.1a2.dist-info/top_level.txt
matplitlib_terminal-0.1a2.dist-info/RECORD
