Metadata-Version: 2.1
Name: matplitlib-terminal
Version: 0.1a2
Summary: Render matplotlib plots in terminal.
Home-page: https://github.com/matrach/matplotlib-terminal
Author: Maciej Matraszek
Author-email: matraszek.maciej@gmail.com
License: MIT
Platform: UNKNOWN
Classifier: Programming Language :: Python :: 3
Classifier: License :: OSI Approved :: MIT License
Classifier: Operating System :: OS Independent
Requires-Python: >=3.6
Requires-Dist: matplotlib
Requires-Dist: img2unicode
Provides-Extra: develop
Requires-Dist: pytest ; extra == 'develop'
Requires-Dist: pytest-cov ; extra == 'develop'
Requires-Dist: sphinx ; extra == 'develop'
Requires-Dist: sphinx-autodoc-typehints ; extra == 'develop'
